lam_middleware/__init__.py
lam_middleware/middleware.py
lam_middleware-0.1.1.dist-info/METADATA
lam_middleware-0.1.1.dist-info/WHEEL
lam_middleware-0.1.1.dist-info/top_level.txt
lam_middleware-0.1.1.dist-info/RECORD
