Metadata-Version: 2.4
Name: lam_middleware
Version: 0.1.1
Summary: Lightweight API Monitoring middleware for Starlette/FastAPI
Author: Rohan Varma
Requires-Python: >=3.9
Requires-Dist: starlette<1.0,>=0.27
Requires-Dist: httpx<1.0,>=0.24
Dynamic: author
Dynamic: requires-dist
Dynamic: requires-python
Dynamic: summary
